Pycsw23ZhongwenWendang/README.md
Pycsw23ZhongwenWendang/__init__.py
Pycsw23ZhongwenWendang/__main__.py
Pycsw23ZhongwenWendang/file.epub
Pycsw23ZhongwenWendang/index.html
Pycsw23ZhongwenWendang/css/__init__.py
Pycsw23ZhongwenWendang/css/annotations.css
Pycsw23ZhongwenWendang/css/main.css
Pycsw23ZhongwenWendang/css/normalize.css
Pycsw23ZhongwenWendang/css/popup.css
Pycsw23ZhongwenWendang/font/__init__.py
Pycsw23ZhongwenWendang/font/fontello.eot
Pycsw23ZhongwenWendang/font/fontello.svg
Pycsw23ZhongwenWendang/font/fontello.ttf
Pycsw23ZhongwenWendang/font/fontello.woff
Pycsw23ZhongwenWendang/img/__init__.py
Pycsw23ZhongwenWendang/img/annotator-glyph-sprite.png
Pycsw23ZhongwenWendang/img/annotator-icon-sprite.png
Pycsw23ZhongwenWendang/img/apple-touch-icon.png
Pycsw23ZhongwenWendang/img/cancelfullscreen.png
Pycsw23ZhongwenWendang/img/close.png
Pycsw23ZhongwenWendang/img/fullscreen.png
Pycsw23ZhongwenWendang/img/loader.gif
Pycsw23ZhongwenWendang/img/menu-icon.png
Pycsw23ZhongwenWendang/img/save.png
Pycsw23ZhongwenWendang/img/saved.png
Pycsw23ZhongwenWendang/img/settings-s.png
Pycsw23ZhongwenWendang/img/settings.png
Pycsw23ZhongwenWendang/img/star.png
Pycsw23ZhongwenWendang/js/__init__.py
Pycsw23ZhongwenWendang/js/epub.js
Pycsw23ZhongwenWendang/js/epub.min.js
Pycsw23ZhongwenWendang/js/epub.min.map
Pycsw23ZhongwenWendang/js/hooks.min.js
Pycsw23ZhongwenWendang/js/hooks.min.map
Pycsw23ZhongwenWendang/js/reader.js
Pycsw23ZhongwenWendang/js/reader.js.map
Pycsw23ZhongwenWendang/js/reader.min.js
Pycsw23ZhongwenWendang/js/reader.min.map
Pycsw23ZhongwenWendang/js/hooks/__init__.py
Pycsw23ZhongwenWendang/js/hooks/extensions/__init__.py
Pycsw23ZhongwenWendang/js/hooks/extensions/highlight.js
Pycsw23ZhongwenWendang/js/libs/__init__.py
Pycsw23ZhongwenWendang/js/libs/jquery.min.js
Pycsw23ZhongwenWendang/js/libs/localforage.min.js
Pycsw23ZhongwenWendang/js/libs/screenfull.js
Pycsw23ZhongwenWendang/js/libs/screenfull.min.js
Pycsw23ZhongwenWendang/js/libs/zip.min.js
pycsw_2_3_zhongwen_wendang-2024.3.5.0.dist-info/METADATA
pycsw_2_3_zhongwen_wendang-2024.3.5.0.dist-info/WHEEL
pycsw_2_3_zhongwen_wendang-2024.3.5.0.dist-info/entry_points.txt
pycsw_2_3_zhongwen_wendang-2024.3.5.0.dist-info/top_level.txt
pycsw_2_3_zhongwen_wendang-2024.3.5.0.dist-info/RECORD
